xpander_sdk/__init__.py
xpander_sdk/consts/__init__.py
xpander_sdk/consts/api_routes.py
xpander_sdk/core/__init__.py
xpander_sdk/core/module_base.py
xpander_sdk/core/state.py
xpander_sdk/core/xpander_api_client.py
xpander_sdk/exceptions/__init__.py
xpander_sdk/exceptions/module_exception.py
xpander_sdk/models/__init__.py
xpander_sdk/models/activity.py
xpander_sdk/models/compactization.py
xpander_sdk/models/configuration.py
xpander_sdk/models/deep_planning.py
xpander_sdk/models/events.py
xpander_sdk/models/frameworks.py
xpander_sdk/models/generic.py
xpander_sdk/models/notifications.py
xpander_sdk/models/orchestrations.py
xpander_sdk/models/shared.py
xpander_sdk/models/user.py
xpander_sdk/modules/__init__.py
xpander_sdk/modules/agents/__init__.py
xpander_sdk/modules/agents/agents_module.py
xpander_sdk/modules/agents/models/__init__.py
xpander_sdk/modules/agents/models/agent.py
xpander_sdk/modules/agents/models/agent_list.py
xpander_sdk/modules/agents/models/knowledge_bases.py
xpander_sdk/modules/agents/sub_modules/__init__.py
xpander_sdk/modules/agents/sub_modules/agent.py
xpander_sdk/modules/agents/utils/__init__.py
xpander_sdk/modules/agents/utils/generic.py
xpander_sdk/modules/backend/__init__.py
xpander_sdk/modules/backend/backend_module.py
xpander_sdk/modules/backend/events_registry.py
xpander_sdk/modules/backend/decorators/__init__.py
xpander_sdk/modules/backend/decorators/on_auth_event.py
xpander_sdk/modules/backend/frameworks/__init__.py
xpander_sdk/modules/backend/frameworks/agno.py
xpander_sdk/modules/backend/frameworks/dispatch.py
xpander_sdk/modules/backend/utils/__init__.py
xpander_sdk/modules/backend/utils/mcp_oauth.py
xpander_sdk/modules/events/__init__.py
xpander_sdk/modules/events/events_module.py
xpander_sdk/modules/events/decorators/__init__.py
xpander_sdk/modules/events/decorators/on_boot.py
xpander_sdk/modules/events/decorators/on_shutdown.py
xpander_sdk/modules/events/decorators/on_task.py
xpander_sdk/modules/events/decorators/on_tool.py
xpander_sdk-2.0.199.dist-info/licenses/LICENSE
xpander_sdk-2.0.199.dist-info/METADATA
xpander_sdk-2.0.199.dist-info/WHEEL
xpander_sdk-2.0.199.dist-info/top_level.txt
xpander_sdk-2.0.199.dist-info/RECORD
