Metadata-Version: 2.4
Name: xpander-sdk
Version: 2.0.199
Summary: xpander.ai Backend-as-a-service for AI Agents - SDK
Home-page: https://www.xpander.ai
Author: xpanderAI
Author-email: dev@xpander.ai
Classifier: Programming Language :: Python :: 3
Classifier: License :: OSI Approved :: MIT License
Classifier: Operating System :: OS Independent
Requires-Python: >=3.9
License-File: LICENSE
Requires-Dist: python-dotenv>=1.2.1
Requires-Dist: packaging>=25.0
Requires-Dist: pydantic>=2.12.5
Requires-Dist: loguru>=0.7.3
Requires-Dist: httpx>=0.28.1
Requires-Dist: httpx_sse>=0.4.3
Requires-Dist: nest-asyncio>=1.6.0
Requires-Dist: strands-agents>=1.20.0
Requires-Dist: openai-agents>=0.6.4
Requires-Dist: python-toon>=0.1.3
Provides-Extra: agno
Requires-Dist: agno; extra == "agno"
Requires-Dist: sqlalchemy; extra == "agno"
Requires-Dist: psycopg[binary,pool]; extra == "agno"
Requires-Dist: greenlet; extra == "agno"
Provides-Extra: dev
Requires-Dist: black; extra == "dev"
Requires-Dist: pre-commit; extra == "dev"
Requires-Dist: pytest; extra == "dev"
Requires-Dist: anthropic; extra == "dev"
Requires-Dist: mcp; extra == "dev"
Requires-Dist: openai; extra == "dev"
Requires-Dist: fireworks-ai; extra == "dev"
Requires-Dist: aioboto3; extra == "dev"
Requires-Dist: google-genai; extra == "dev"
Dynamic: author
Dynamic: author-email
Dynamic: classifier
Dynamic: description
Dynamic: description-content-type
Dynamic: home-page
Dynamic: license-file
Dynamic: provides-extra
Dynamic: requires-dist
Dynamic: requires-python
Dynamic: summary
